Authcode-1.6.0.dist-info/DESCRIPTION.rst
Authcode-1.6.0.dist-info/METADATA
Authcode-1.6.0.dist-info/RECORD
Authcode-1.6.0.dist-info/WHEEL
Authcode-1.6.0.dist-info/metadata.json
Authcode-1.6.0.dist-info/top_level.txt
authcode/__init__.py
authcode/_compat.py
authcode/auth.py
authcode/auth_authentication_mixin.py
authcode/auth_authorization_mixin.py
authcode/auth_views_mixin.py
authcode/constants.py
authcode/models.py
authcode/utils.py
authcode/views.py
authcode/setups/__init__.py
authcode/setups/setup_for_bottle.py
authcode/setups/setup_for_flask.py
authcode/setups/setup_for_shake.py
authcode/templates/base.html
authcode/templates/change-password.html
authcode/templates/reset-password-email.html
authcode/templates/reset-password.html
authcode/templates/sign-in.html
authcode/templates/styles.css
authcode/wsgi/__init__.py
authcode/wsgi/bottle.py
authcode/wsgi/werkzeug.py
