Metadata-Version: 2.0
Name: Authcode
Version: 1.6.0
Summary: Awesome authentication code
Home-page: http://github.com/jpscaletti/authcode
Author: Juan-Pablo Scaletti
Author-email: juanpablo@lucumalabs.com
License: MIT license (see LICENSE)
Platform: UNKNOWN
Classifier: Development Status :: 5 - Production/Stable
Classifier: Environment :: Web Environment
Classifier: Intended Audience :: Developers
Classifier: License :: OSI Approved :: MIT License
Classifier: Programming Language :: Python :: 2
Classifier: Programming Language :: Python :: 2.6
Classifier: Programming Language :: Python :: 2.7
Classifier: Programming Language :: Python :: 3
Classifier: Programming Language :: Python :: 3.3
Classifier: Programming Language :: Python :: 3.4
Classifier: Programming Language :: Python :: Implementation :: PyPy
Requires-Dist: passlib (>=1.6.1)
Requires-Dist: sqlalchemy (>=0.8.2)
